cs_rfm/__init__.py
cs_rfm/problemsolver.py
customersegmentationrfm-0.0.1.dist-info/LICENSE
customersegmentationrfm-0.0.1.dist-info/METADATA
customersegmentationrfm-0.0.1.dist-info/WHEEL
customersegmentationrfm-0.0.1.dist-info/top_level.txt
customersegmentationrfm-0.0.1.dist-info/RECORD
