Metadata-Version: 2.1
Name: customersegmentationrfm
Version: 0.0.1
Summary: Customer Segmentation: RFM Anlaysis
Home-page: https://github.com/NMeliksetyan/customer_segmentation
Author: Nune Meliksetyan
License: UNKNOWN
Platform: UNKNOWN
Classifier: Programming Language :: Python :: 3
Classifier: License :: OSI Approved :: MIT License
Classifier: Operating System :: OS Independent
Requires-Python: >=3.6
License-File: LICENSE
Requires-Dist: pandas (>=1.2.4)
Requires-Dist: numpy (>=1.20.1)
Requires-Dist: matplotlib (>=3.3.4)
